nsfwguard/__init__.py
nsfwguard/api.py
nsfwguard/batch.py
nsfwguard/cli.py
nsfwguard/heatmap.py
nsfwguard/image.py
nsfwguard/policy.py
nsfwguard/telegram.py
nsfwguard/url.py
nsfwguard/video.py
nsfwguard-1.0.1.dist-info/licenses/LICENSE
nsfwguard-1.0.1.dist-info/METADATA
nsfwguard-1.0.1.dist-info/WHEEL
nsfwguard-1.0.1.dist-info/entry_points.txt
nsfwguard-1.0.1.dist-info/top_level.txt
nsfwguard-1.0.1.dist-info/RECORD
