Metadata-Version: 2.4
Name: nsfwguard
Version: 1.0.1
Summary: GPU-accelerated NSFW content detection for images, videos, and URLs
Author: LISA-KOREA
License: MIT
Project-URL: Homepage, https://github.com/LISA-KOREA
Requires-Python: >=3.8
License-File: LICENSE
Requires-Dist: torch
Requires-Dist: torchvision
Requires-Dist: nudenet
Requires-Dist: opencv-python
Requires-Dist: pillow
Requires-Dist: requests
Requires-Dist: fastapi
Requires-Dist: uvicorn
Provides-Extra: telegram
Requires-Dist: pyrofork; extra == "telegram"
Dynamic: license-file
